pytest_describe_it/__init__.py
pytest_describe_it/_plugin.py
pytest_describe_it-0.1.0.dist-info/LICENSE
pytest_describe_it-0.1.0.dist-info/METADATA
pytest_describe_it-0.1.0.dist-info/WHEEL
pytest_describe_it-0.1.0.dist-info/entry_points.txt
pytest_describe_it-0.1.0.dist-info/top_level.txt
pytest_describe_it-0.1.0.dist-info/RECORD
