Metadata-Version: 2.1
Name: pytest-describe-it
Version: 0.1.0
Summary: plugin for rich text descriptions
Home-page: https://github.com/tkukushkin/pytest-describe-it
Author: Timofey Kukushkin
Author-email: tima@kukushkin.me
License: MIT
Project-URL: Source, https://github.com/tkukushkin/pytest-describe-it
Platform: UNKNOWN
Classifier: Development Status :: 4 - Beta
Classifier: Environment :: Plugins
Classifier: Framework :: Pytest
Classifier: Intended Audience :: Developers
Classifier: License :: OSI Approved :: MIT License
Classifier: Operating System :: OS Independent
Classifier: Programming Language :: Python :: 2
Classifier: Programming Language :: Python :: 2.7
Classifier: Programming Language :: Python :: 3
Classifier: Programming Language :: Python :: 3.6
Classifier: Programming Language :: Python :: 3.7
Classifier: Programming Language :: Python :: 3.8
Classifier: Topic :: Software Development :: Libraries :: Python Modules
Classifier: Topic :: Software Development :: Testing
Requires-Dist: pytest
Requires-Dist: typing ; python_version < "3"
Provides-Extra: test
Requires-Dist: pycodestyle ; extra == 'test'
